setup.py
tabfileio/__init__.py
tabfileio/__main__.py
tabfileio/excelio.py
tabfileio/hdf5.py
tabfileio/interface.py
tabfileio/jsonio.py
tabfileio/pickleio.py
tabfileio/textio.py
tabfileio/utils.py
tabfileio.egg-info/PKG-INFO
tabfileio.egg-info/SOURCES.txt
tabfileio.egg-info/dependency_links.txt
tabfileio.egg-info/not-zip-safe
tabfileio.egg-info/requires.txt
tabfileio.egg-info/top_level.txt